Workbook

Sheet Tarifas_Referencia
A1: TABULADOR OFICIAL DE TARIFAS - MUNET (2026)
A3: Espacio | B3: Privado: Viernes/Sábado (Diario) | C3: Privado: Lun-Jue (Diario) | D3: Montaje/Desmontaje (Diario) | E3: Público: Garantía Mínima | F3: Público: % Boletos | G3: Renta 4 Horas | H3: Renta Día Completo
A4: Explanada Principal | B4: 350000 | C4: 300000 | D4: 150000 | E4: 400000 | F4: 0.12 | G4: 0 | H4: 350000
A5: Foro (Búnker) | B5: 250000 | C5: 200000 | D5: 100000 | E5: 350000 | F5: 0.12 | G5: 0 | H5: 250000
A6: Lobby Principal | B6: 280000 | C6: 230000 | D6: 150000 | E6: 0 | F6: 0 | G6: 0 | H6: 280000
A7: Auditorio Principal | B7: 0 | C7: 0 | D7: 0 | E7: 60000 | F7: 0.12 | G7: 25000 | H7: 60000
A8: Jardín Social | B8: 0 | C8: 0 | D8: 0 | E8: 0 | F8: 0 | G8: 0 | H8: 70000
A9: Velaria | B9: 0 | C9: 0 | D9: 0 | E9: 0 | F9: 0 | G9: 0 | H9: 80000
A10: Sala de Exposiciones (Blackbox) | B10: 150000 | C10: 150000 | D10: 75000 | E10: 0 | F10: 0 | G10: 0 | H10: 150000
A11: Salas de Capacitación | B11: 0 | C11: 0 | D11: 0 | E11: 0 | F11: 0 | G11: 10000 | H11: 20000

Sheet Simulador_Costos
B2: MUNET - SIMULADOR OPERATIVO Y DE COSTOS PARA EVENTOS (2026)
B4: 1. DATOS GENERALES DEL EVENTO
B5: Nombre del Evento: | C5: Ej. Congreso de Energía 2026 | E5: NOTAS LOGÍSTICAS IMPORTANTES: • Eventos Privados: Tarifas diferenciadas para fin de semana (Vie-Sáb) y resto de la semana (Lun-Jue). • Eventos Públicos: Se calcula sobre Garantía Mínima o el 12% de la venta de boletos (lo que resulte mayor). • Regla de Ocupación: Para eventos de más de 5 días de ocupación total, se puede prescindir de la garantía mínima y operar únicamente con el 12% de porcentaje de venta de boletos (Sujeto a aprobación comercial del MUNET). • Operador Autorizado: BÚNKER es el socio estratégico in-house oficial para coordinar toda la logística, producción técnica, rigging, catering y operaciones de montaje.
B6: Nombre del Cliente/Organizador: | C6: Ej. Bunker Creatividad Empresarial
B7: Fecha del Evento: | C7: 2026-10-15
B8: Tipo de Evento (Dropdown): | C8: Privado
B9: Ingresos Estimados por Taquilla (Público): | C9: 0
B10: Descuento Especial Aplicado (%): | C10: 0
B12: 2. CONFIGURACIÓN DE ESPACIOS A RENTAR
B13: Espacio a Rentar | C13: Días Evento (Vie/Sáb) | D13: Días Evento (Lun-Jue) | E13: Días Montaje/Desmon. | F13: Auditorio/Salas: Bloques 4 hrs | G13: Auditorio/Salas: Días Compl. | H13: Costo Renta Evento | I13: Costo Montaje/Desmon. | J13: Garantía Mínima (Público) | K13: TOTAL ESPACIO
B14: Explanada Principal | C14: 0 | D14: 0 | E14: 0 | F14: 0 | G14: 0 | H14: =IF($C$8="Privado", (C14*Tarifas_Referencia!B4) + (D14*Tarifas_Referencia!C4), 0) | I14: =E14*Tarifas_Referencia!D4 | J14: =IF($C$8="Público", IF((C14+D14+E14+G14)>5, 0, (C14+D14+G14)*Tarifas_Referencia!E4), 0) | K14: =IF($C$8="Privado", H14+I14, MAX(J14, Tarifas_Referencia!F4*$C$9) + I14)
B15: Foro (Búnker) | C15: 0 | D15: 0 | E15: 0 | F15: 0 | G15: 0 | H15: =IF($C$8="Privado", (C15*Tarifas_Referencia!B5) + (D15*Tarifas_Referencia!C5), 0) | I15: =E15*Tarifas_Referencia!D5 | J15: =IF($C$8="Público", IF((C15+D15+E15+G15)>5, 0, (C15+D15+G15)*Tarifas_Referencia!E5), 0) | K15: =IF($C$8="Privado", H15+I15, MAX(J15, Tarifas_Referencia!F5*$C$9) + I15)
B16: Lobby Principal | C16: 0 | D16: 0 | E16: 0 | F16: 0 | G16: 0 | H16: =IF($C$8="Privado", (C16*Tarifas_Referencia!B6) + (D16*Tarifas_Referencia!C6), 0) | I16: =E16*Tarifas_Referencia!D6 | J16: =IF($C$8="Público", IF((C16+D16+E16+G16)>5, 0, (C16+D16+G16)*Tarifas_Referencia!E6), 0) | K16: =IF($C$8="Privado", H16+I16, MAX(J16, Tarifas_Referencia!F6*$C$9) + I16)
B17: Auditorio Principal | C17: 0 | D17: 0 | E17: 0 | F17: 0 | G17: 0 | H17: =IF($C$8="Privado", (F17*Tarifas_Referencia!G7) + (G17*Tarifas_Referencia!H7), 0) | I17: =E17*Tarifas_Referencia!D7 | J17: =IF($C$8="Público", IF((C17+D17+E17+G17)>5, 0, (C17+D17+G17)*Tarifas_Referencia!E7), 0) | K17: =IF($C$8="Privado", H17+I17, MAX(J17, Tarifas_Referencia!F7*$C$9) + I17)
B18: Jardín Social | C18: 0 | D18: 0 | E18: 0 | F18: 0 | G18: 0 | H18: =IF($C$8="Privado", (C18*Tarifas_Referencia!B8) + (D18*Tarifas_Referencia!C8), 0) | I18: =E18*Tarifas_Referencia!D8 | J18: =IF($C$8="Público", IF((C18+D18+E18+G18)>5, 0, (C18+D18+G18)*Tarifas_Referencia!E8), 0) | K18: =IF($C$8="Privado", H18+I18, MAX(J18, Tarifas_Referencia!F8*$C$9) + I18)
B19: Velaria | C19: 0 | D19: 0 | E19: 0 | F19: 0 | G19: 0 | H19: =IF($C$8="Privado", (C19*Tarifas_Referencia!B9) + (D19*Tarifas_Referencia!C9), 0) | I19: =E19*Tarifas_Referencia!D9 | J19: =IF($C$8="Público", IF((C19+D19+E19+G19)>5, 0, (C19+D19+G19)*Tarifas_Referencia!E9), 0) | K19: =IF($C$8="Privado", H19+I19, MAX(J19, Tarifas_Referencia!F9*$C$9) + I19)
B20: Sala de Exposiciones (Blackbox) | C20: 0 | D20: 0 | E20: 0 | F20: 0 | G20: 0 | H20: =IF($C$8="Privado", (C20*Tarifas_Referencia!B10) + (D20*Tarifas_Referencia!C10), 0) | I20: =E20*Tarifas_Referencia!D10 | J20: =IF($C$8="Público", IF((C20+D20+E20+G20)>5, 0, (C20+D20+G20)*Tarifas_Referencia!E10), 0) | K20: =IF($C$8="Privado", H20+I20, MAX(J20, Tarifas_Referencia!F10*$C$9) + I20)
B21: Salas de Capacitación | C21: 0 | D21: 0 | E21: 0 | F21: 0 | G21: 0 | H21: =IF($C$8="Privado", (F21*Tarifas_Referencia!G11) + (G21*Tarifas_Referencia!H11), 0) | I21: =E21*Tarifas_Referencia!D11 | J21: =IF($C$8="Público", IF((C21+D21+E21+G21)>5, 0, (C21+D21+G21)*Tarifas_Referencia!E11), 0) | K21: =IF($C$8="Privado", H21+I21, MAX(J21, Tarifas_Referencia!F11*$C$9) + I21)
B22: Subtotal Renta de Espacios: | K22: =SUM(K14:K21)
B24: 3. ESTIMACIÓN DE SERVICIOS ADICIONALES Y LOGÍSTICA
B25: Concepto del Servicio | C25: Tipo Costo | D25: Cantidad / Días | E25: Tarifa Unitaria | K25: TOTAL SERVICIO
B26: Coordinación de Producción General (BÚNKER) | C26: Diario | D26: 1 | E26: 15000 | K26: =IF(C26="Diario", D26*E26, E26)
B27: Personal de Seguridad Privada (Turno 12h/elemento) | C27: Diario | D27: 10 | E27: 1500 | K27: =IF(C27="Diario", D27*E27, E27)
B28: Personal de Limpieza y Gestión de Residuos | C28: Diario | D28: 8 | E28: 1200 | K28: =IF(C28="Diario", D28*E28, E28)
B29: Supervisión de Mantenimiento y Planta | C29: Diario | D29: 2 | E29: 2500 | K29: =IF(C29="Diario", D29*E29, E29)
B30: Unidad Médica, Ambulancia y Paramédicos | C30: Diario | D30: 1 | E30: 8500 | K30: =IF(C30="Diario", D30*E30, E30)
B31: Carpeta de Protección Civil y Trámites | C31: Fijo | D31: 1 | E31: 35000 | K31: =IF(C31="Diario", D31*E31, E31)
B32: Planta de Luz Auxiliar e Ingeniería Técnica | C32: Diario | D32: 1 | E32: 22000 | K32: =IF(C32="Diario", D32*E32, E32)
B33: Catering y Alimentos & Bebidas (Presupuesto Base) | C33: Fijo | D33: 1 | E33: 120000 | K33: =IF(C33="Diario", D33*E33, E33)
B34: Subtotal Servicios y Operación: | K34: =SUM(K26:K33)
B36: 4. RESUMEN DE COTIZACIÓN Y PRESUPUESTO
B37: Subtotal Renta de Espacios: | K37: =K22
B38: Subtotal Servicios Adicionales: | K38: =K34
B39: Descuento Especial sobre Renta (%): | K39: =$C$10
B40: Monto Descuento Aplicado: | K40: =K39*K37
B41: TOTAL NETO ESTIMADO: | K41: =K37+K38-K40
